README.rst
setup.cfg
setup.py
netbox_netdev_inventory/__init__.py
netbox_netdev_inventory/__main__.py
netbox_netdev_inventory/config.py
netbox_netdev_inventory/devices_list.py
netbox_netdev_inventory/exceptions.py
netbox_netdev_inventory/importer.py
netbox_netdev_inventory/push.py
netbox_netdev_inventory/tools.py
netbox_netdev_inventory.egg-info/PKG-INFO
netbox_netdev_inventory.egg-info/SOURCES.txt
netbox_netdev_inventory.egg-info/dependency_links.txt
netbox_netdev_inventory.egg-info/entry_points.txt
netbox_netdev_inventory.egg-info/not-zip-safe
netbox_netdev_inventory.egg-info/requires.txt
netbox_netdev_inventory.egg-info/top_level.txt
netbox_netdev_inventory/vendors/__init__.py
netbox_netdev_inventory/vendors/base.py
netbox_netdev_inventory/vendors/constants.py
netbox_netdev_inventory/vendors/cisco/__init__.py
netbox_netdev_inventory/vendors/cisco/base.py
netbox_netdev_inventory/vendors/cisco/constants.py
netbox_netdev_inventory/vendors/cisco/ios.py
netbox_netdev_inventory/vendors/cisco/nxos.py
netbox_netdev_inventory/vendors/juniper/__init__.py
netbox_netdev_inventory/vendors/juniper/base.py
netbox_netdev_inventory/vendors/juniper/constants.py