Metadata-Version: 1.1
Name: netbox-netdev-inventory
Version: 0.2.3
Summary: Microservice import into netbox devices in production
Home-page: https://github.com/VictorPavlushin/netbox-netdev-inventory
Author: Victor
Author-email: victor@pavlushin.info
License: UNKNOWN
Keywords: netbox_netdev_inventory
Platform: UNKNOWN
Classifier: Intended Audience :: Developers
Classifier: Natural Language :: English
Classifier: Programming Language :: Python :: 3
Classifier: Programming Language :: Python :: 3.5
Classifier: Programming Language :: Python :: 3.6
Classifier: Programming Language :: Python :: 3.7
